{
    "os": "Linux-4.19.112+-x86_64-with-Ubuntu-18.04-bionic",
    "python": "3.7.10",
    "heartbeatAt": "2021-03-01T16:52:09.266054",
    "startedAt": "2021-03-01T16:52:07.075837",
    "docker": null,
    "gpu": "Tesla P4",
    "gpu_count": 1,
    "cpu_count": 2,
    "cuda": "10.1.243",
    "args": [
        "--mode",
        "train",
        "--n-shot",
        "5",
        "--n-eval",
        "15",
        "--n-class",
        "5",
        "--input-size",
        "4",
        "--hidden-size",
        "20",
        "--lr",
        "1e-3",
        "--episode",
        "50000",
        "--episode-val",
        "100",
        "--epoch",
        "8",
        "--batch-size",
        "25",
        "--image-size",
        "84",
        "--grad-clip",
        "0.25",
        "--bn-momentum",
        "0.95",
        "--bn-eps",
        "1e-3",
        "--data",
        "miniimagenet",
        "--data-root",
        "data/miniImagenet/",
        "--pin-mem",
        "True",
        "--log-freq",
        "50",
        "--val-freq",
        "1000"
    ],
    "state": "running",
    "codePath": "main.py",
    "program": "main.py",
    "git": {
        "remote": "https://github.com/joeljosephjin/meta-learning-lstm-pytorch.git",
        "commit": "ea020d58f3d3fcacefad7f0afb338d445d741658"
    },
    "email": null,
    "root": "/content/meta-learning-lstm-pytorch",
    "host": "a7b8ae422820",
    "username": "root",
    "executable": "/usr/bin/python3"
}
